sine_gen.v
module sine_gen(
    input clk, rst,
    output reg [7:0] sine_out
);
    // Initialize 16-bit phase accumulator
    reg [15:0] phase_acc = 0;

    // Phase increment (controls frequency)
    parameter PHASE_INC = 500;

    // Sine Lookup Table (LUT)
    reg [7:0] sine_table [0:255];

    // Load precomputed sine values
    initial begin
      $readmemh("sine_lut.hex", sine_table);
    end

    always @ (posedge clk or posedge rst) begin
        if (rst)
            // Reset phase accumulator to 0 on rst
            phase_acc <= 0;
        else
            // Incrememnt phase accumulator on every posedge
            phase_acc <= phase_acc + PHASE_INC;
    end

    // Set sine_out value every time phase accumulator changes
    // Last 8 bits are used to fetch sine value
    always @ (*) begin
        sine_out = sine_table[phase_acc[15:8]];
    end

endmodule

sine_gen_tb.v
`timescale 1ns/1ps

module sine_gen_tb();
    // Test inputs
    reg clk;
    reg rst;

    // Test outputs
    wire [7:0] sine_out;

    sine_gen uut (
        clk,
        rst,
        sine_out
    );

    // Clock gen
    always #10 clk = ~clk; // 20 ns period -> 50 MHz

    initial begin
        $dumpfile("sine_gen_tb.vcd");
        $dumpvars(0, sine_gen_tb);

        // Init signals
        clk = 0;
        rst = 1;
        #50 rst = 0;// release reset after 50 ns

        #500_000 // run for 500,000 ns (0.5 ms)

        $finish;

    end
endmodule

sine_gen_tb.vcd
$date
	Wed Feb 19 23:14:51 2025
$end
$version
	Icarus Verilog
$end
$timescale
	1ps
$end
$scope module sine_gen_tb $end
$var wire 8 ! sine_out [7:0] $end
$var reg 1 " clk $end
$var reg 1 # rst $end
$scope module uut $end
$var wire 1 " clk $end
$var wire 1 # rst $end
$var parameter 32 $ PHASE_INC $end
$var reg 16 % phase_acc [15:0] $end
$var reg 8 & sine_out [7:0] $end
$upscope $end
$upscope $end
$enddefinitions $end
$comment Show the parameter values. $end
$dumpall
b111110100 $
$end
#0
$dumpvars
b1111111 &
b0 %
1#
0"
b1111111 !
$end
#10000
1"
#20000
0"
#30000
1"
#40000
0"
#50000
b10000010 !
b10000010 &
b111110100 %
1"
0#
#60000
0"
#70000
b10001000 !
b10001000 &
b1111101000 %
1"
#80000
0"
#90000
b10001111 !
b10001111 &
b10111011100 %
1"
#100000
0"
#110000
b10010101 !
b10010101 &
b11111010000 %
1"
#120000
0"
#130000
b10011011 !
b10011011 &
b100111000100 %
1"
#140000
0"
#150000
b10100001 !
b10100001 &
b101110111000 %
1"
#160000
0"
#170000
b10100111 !
b10100111 &
b110110101100 %
1"
#180000
0"
#190000
b10101101 !
b10101101 &
b111110100000 %
1"
#200000
0"
#210000
b10110011 !
b10110011 &
b1000110010100 %
1"
#220000
0"
#230000
b10111000 !
b10111000 &
b1001110001000 %
1"
#240000
0"
#250000
b10111110 !
b10111110 &
b1010101111100 %
1"
#260000
0"
#270000
b11000011 !
b11000011 &
b1011101110000 %
1"
#280000
0"
#290000
b11001000 !
b11001000 &
b1100101100100 %
1"
#300000
0"
#310000
b11001101 !
b11001101 &
b1101101011000 %
1"
#320000
0"
#330000
b11010010 !
b11010010 &
b1110101001100 %
1"
#340000
0"
#350000
b11010111 !
b11010111 &
b1111101000000 %
1"
#360000
0"
#370000
b11011011 !
b11011011 &
b10000100110100 %
1"
#380000
0"
#390000
b11100000 !
b11100000 &
b10001100101000 %
1"
#400000
0"
#410000
b11100100 !
b11100100 &
b10010100011100 %
1"
#420000
0"
#430000
b11100111 !
b11100111 &
b10011100010000 %
1"
#440000
0"
#450000
b11101011 !
b11101011 &
b10100100000100 %
1"
#460000
0"
#470000
b11101100 !
b11101100 &
b10101011111000 %
1"
#480000
0"
#490000
b11101111 !
b11101111 &
b10110011101100 %
1"
#500000
0"
#510000
b11110010 !
b11110010 &
b10111011100000 %
1"
#520000
0"
#530000
b11110101 !
b11110101 &
b11000011010100 %
1"
#540000
0"
#550000
b11110111 !
b11110111 &
b11001011001000 %
1"
#560000
0"
#570000
b11111001 !
b11111001 &
b11010010111100 %
1"
#580000
0"
#590000
b11111011 !
b11111011 &
b11011010110000 %
1"
#600000
0"
#610000
b11111100 !
b11111100 &
b11100010100100 %
1"
#620000
0"
#630000
b11111101 !
b11111101 &
b11101010011000 %
1"
#640000
0"
#650000
b11111110 !
b11111110 &
b11110010001100 %
1"
#660000
0"
#670000
b11111010000000 %
1"
#680000
0"
#690000
b11111111 !
b11111111 &
b100000001110100 %
1"
#700000
0"
#710000
b11111110 !
b11111110 &
b100001001101000 %
1"
#720000
0"
#730000
b100010001011100 %
1"
#740000
0"
#750000
b11111101 !
b11111101 &
b100011001010000 %
1"
#760000
0"
#770000
b11111100 !
b11111100 &
b100100001000100 %
1"
#780000
0"
#790000
b11111011 !
b11111011 &
b100101000111000 %
1"
#800000
0"
#810000
b11111001 !
b11111001 &
b100110000101100 %
1"
#820000
0"
#830000
b11110111 !
b11110111 &
b100111000100000 %
1"
#840000
0"
#850000
b11110101 !
b11110101 &
b101000000010100 %
1"
#860000
0"
#870000
b11110010 !
b11110010 &
b101001000001000 %
1"
#880000
0"
#890000
b11110001 !
b11110001 &
b101001111111100 %
1"
#900000
0"
#910000
b11101110 !
b11101110 &
b101010111110000 %
1"
#920000
0"
#930000
b11101011 !
b11101011 &
b101011111100100 %
1"
#940000
0"
#950000
b11100111 !
b11100111 &
b101100111011000 %
1"
#960000
0"
#970000
b11100100 !
b11100100 &
b101101111001100 %
1"
#980000
0"
#990000
b11100000 !
b11100000 &
b101110111000000 %
1"
#1000000
0"
#1010000
b11011011 !
b11011011 &
b101111110110100 %
1"
#1020000
0"
#1030000
b11010111 !
b11010111 &
b110000110101000 %
1"
#1040000
0"
#1050000
b11010010 !
b11010010 &
b110001110011100 %
1"
#1060000
0"
#1070000
b11001101 !
b11001101 &
b110010110010000 %
1"
#1080000
0"
#1090000
b11001000 !
b11001000 &
b110011110000100 %
1"
#1100000
0"
#1110000
b11000011 !
b11000011 &
b110100101111000 %
1"
#1120000
0"
#1130000
b10111110 !
b10111110 &
b110101101101100 %
1"
#1140000
0"
#1150000
b10111000 !
b10111000 &
b110110101100000 %
1"
#1160000
0"
#1170000
b10110011 !
b10110011 &
b110111101010100 %
1"
#1180000
0"
#1190000
b10101101 !
b10101101 &
b111000101001000 %
1"
#1200000
0"
#1210000
b10100111 !
b10100111 &
b111001100111100 %
1"
#1220000
0"
#1230000
b10100001 !
b10100001 &
b111010100110000 %
1"
#1240000
0"
#1250000
b10011011 !
b10011011 &
b111011100100100 %
1"
#1260000
0"
#1270000
b10010101 !
b10010101 &
b111100100011000 %
1"
#1280000
0"
#1290000
b10001111 !
b10001111 &
b111101100001100 %
1"
#1300000
0"
#1310000
b10001000 !
b10001000 &
b111110100000000 %
1"
#1320000
0"
#1330000
b10000101 !
b10000101 &
b111111011110100 %
1"
#1340000
0"
#1350000
b1111111 !
b1111111 &
b1000000011101000 %
1"
#1360000
0"
#1370000
b1111001 !
b1111001 &
b1000001011011100 %
1"
#1380000
0"
#1390000
b1110011 !
b1110011 &
b1000010011010000 %
1"
#1400000
0"
#1410000
b1101100 !
b1101100 &
b1000011011000100 %
1"
#1420000
0"
#1430000
b1100110 !
b1100110 &
b1000100010111000 %
1"
#1440000
0"
#1450000
b1100000 !
b1100000 &
b1000101010101100 %
1"
#1460000
0"
#1470000
b1011010 !
b1011010 &
b1000110010100000 %
1"
#1480000
0"
#1490000
b1010100 !
b1010100 &
b1000111010010100 %
1"
#1500000
0"
#1510000
b1001110 !
b1001110 &
b1001000010001000 %
1"
#1520000
0"
#1530000
b1001000 !
b1001000 &
b1001001001111100 %
1"
#1540000
0"
#1550000
b1000011 !
b1000011 &
b1001010001110000 %
1"
#1560000
0"
#1570000
b111101 !
b111101 &
b1001011001100100 %
1"
#1580000
0"
#1590000
b111000 !
b111000 &
b1001100001011000 %
1"
#1600000
0"
#1610000
b110011 !
b110011 &
b1001101001001100 %
1"
#1620000
0"
#1630000
b101110 !
b101110 &
b1001110001000000 %
1"
#1640000
0"
#1650000
b101001 !
b101001 &
b1001111000110100 %
1"
#1660000
0"
#1670000
b100101 !
b100101 &
b1010000000101000 %
1"
#1680000
0"
#1690000
b100001 !
b100001 &
b1010001000011100 %
1"
#1700000
0"
#1710000
b11100 !
b11100 &
b1010010000010000 %
1"
#1720000
0"
#1730000
b11001 !
b11001 &
b1010011000000100 %
1"
#1740000
0"
#1750000
b10111 !
b10111 &
b1010011111111000 %
1"
#1760000
0"
#1770000
b10011 !
b10011 &
b1010100111101100 %
1"
#1780000
0"
#1790000
b10000 !
b10000 &
b1010101111100000 %
1"
#1800000
0"
#1810000
b1101 !
b1101 &
b1010110111010100 %
1"
#1820000
0"
#1830000
b1010 !
b1010 &
b1010111111001000 %
1"
#1840000
0"
#1850000
b1000 !
b1000 &
b1011000110111100 %
1"
#1860000
0"
#1870000
b110 !
b110 &
b1011001110110000 %
1"
#1880000
0"
#1890000
b100 !
b100 &
b1011010110100100 %
1"
#1900000
0"
#1910000
b11 !
b11 &
b1011011110011000 %
1"
#1920000
0"
#1930000
b1 !
b1 &
b1011100110001100 %
1"
#1940000
0"
#1950000
b0 !
b0 &
b1011101110000000 %
1"
#1960000
0"
#1970000
b1011110101110100 %
1"
#1980000
0"
#1990000
b1011111101101000 %
1"
#2000000
0"
#2010000
b1100000101011100 %
1"
#2020000
0"
#2030000
b1100001101010000 %
1"
#2040000
0"
#2050000
b1100010101000100 %
1"
#2060000
0"
#2070000
b1 !
b1 &
b1100011100111000 %
1"
#2080000
0"
#2090000
b11 !
b11 &
b1100100100101100 %
1"
#2100000
0"
#2110000
b100 !
b100 &
b1100101100100000 %
1"
#2120000
0"
#2130000
b110 !
b110 &
b1100110100010100 %
1"
#2140000
0"
#2150000
b1000 !
b1000 &
b1100111100001000 %
1"
#2160000
0"
#2170000
b1001 !
b1001 &
b1101000011111100 %
1"
#2180000
0"
#2190000
b1100 !
b1100 &
b1101001011110000 %
1"
#2200000
0"
#2210000
b1111 !
b1111 &
b1101010011100100 %
1"
#2220000
0"
#2230000
b10010 !
b10010 &
b1101011011011000 %
1"
#2240000
0"
#2250000
b10101 !
b10101 &
b1101100011001100 %
1"
#2260000
0"
#2270000
b11001 !
b11001 &
b1101101011000000 %
1"
#2280000
0"
#2290000
b11100 !
b11100 &
b1101110010110100 %
1"
#2300000
0"
#2310000
b100001 !
b100001 &
b1101111010101000 %
1"
#2320000
0"
#2330000
b100101 !
b100101 &
b1110000010011100 %
1"
#2340000
0"
#2350000
b101001 !
b101001 &
b1110001010010000 %
1"
#2360000
0"
#2370000
b101110 !
b101110 &
b1110010010000100 %
1"
#2380000
0"
#2390000
b110011 !
b110011 &
b1110011001111000 %
1"
#2400000
0"
#2410000
b111000 !
b111000 &
b1110100001101100 %
1"
#2420000
0"
#2430000
b111101 !
b111101 &
b1110101001100000 %
1"
#2440000
0"
#2450000
b1000011 !
b1000011 &
b1110110001010100 %
1"
#2460000
0"
#2470000
b1001000 !
b1001000 &
b1110111001001000 %
1"
#2480000
0"
#2490000
b1001110 !
b1001110 &
b1111000000111100 %
1"
#2500000
0"
#2510000
b1010100 !
b1010100 &
b1111001000110000 %
1"
#2520000
0"
#2530000
b1011010 !
b1011010 &
b1111010000100100 %
1"
#2540000
0"
#2550000
b1100000 !
b1100000 &
b1111011000011000 %
1"
#2560000
0"
#2570000
b1100110 !
b1100110 &
b1111100000001100 %
1"
#2580000
0"
#2590000
b1101100 !
b1101100 &
b1111101000000000 %
1"
#2600000
0"
#2610000
b1101111 !
b1101111 &
b1111101111110100 %
1"
#2620000
0"
#2630000
b1110110 !
b1110110 &
b1111110111101000 %
1"
#2640000
0"
#2650000
b1111100 !
b1111100 &
b1111111111011100 %
1"
#2660000
0"
#2670000
b10000010 !
b10000010 &
b111010000 %
1"
#2680000
0"
#2690000
b10001000 !
b10001000 &
b1111000100 %
1"
#2700000
0"
#2710000
b10001111 !
b10001111 &
b10110111000 %
1"
#2720000
0"
#2730000
b10010101 !
b10010101 &
b11110101100 %
1"
#2740000
0"
#2750000
b10011011 !
b10011011 &
b100110100000 %
1"
#2760000
0"
#2770000
b10100001 !
b10100001 &
b101110010100 %
1"
#2780000
0"
#2790000
b10100111 !
b10100111 &
b110110001000 %
1"
#2800000
0"
#2810000
b10101101 !
b10101101 &
b111101111100 %
1"
#2820000
0"
#2830000
b10110011 !
b10110011 &
b1000101110000 %
1"
#2840000
0"
#2850000
b10111000 !
b10111000 &
b1001101100100 %
1"
#2860000
0"
#2870000
b10111110 !
b10111110 &
b1010101011000 %
1"
#2880000
0"
#2890000
b11000011 !
b11000011 &
b1011101001100 %
1"
#2900000
0"
#2910000
b11001000 !
b11001000 &
b1100101000000 %
1"
#2920000
0"
#2930000
b11001101 !
b11001101 &
b1101100110100 %
1"
#2940000
0"
#2950000
b11010010 !
b11010010 &
b1110100101000 %
1"
#2960000
0"
#2970000
b11010111 !
b11010111 &
b1111100011100 %
1"
#2980000
0"
#2990000
b11011011 !
b11011011 &
b10000100010000 %
1"
#3000000
0"
#3010000
b11100000 !
b11100000 &
b10001100000100 %
1"
#3020000
0"
#3030000
b11100010 !
b11100010 &
b10010011111000 %
1"
#3040000
0"
#3050000
b11100101 !
b11100101 &
b10011011101100 %
1"
#3060000
0"
#3070000
b11101001 !
b11101001 &
b10100011100000 %
1"
#3080000
0"
#3090000
b11101100 !
b11101100 &
b10101011010100 %
1"
#3100000
0"
#3110000
b11101111 !
b11101111 &
b10110011001000 %
1"
#3120000
0"
#3130000
b11110010 !
b11110010 &
b10111010111100 %
1"
#3140000
0"
#3150000
b11110101 !
b11110101 &
b11000010110000 %
1"
#3160000
0"
#3170000
b11110111 !
b11110111 &
b11001010100100 %
1"
#3180000
0"
#3190000
b11111001 !
b11111001 &
b11010010011000 %
1"
#3200000
0"
#3210000
b11111011 !
b11111011 &
b11011010001100 %
1"
#3220000
0"
#3230000
b11111100 !
b11111100 &
b11100010000000 %
1"
#3240000
0"
#3250000
b11111101 !
b11111101 &
b11101001110100 %
1"
#3260000
0"
#3270000
b11111110 !
b11111110 &
b11110001101000 %
1"
#3280000
0"
#3290000
b11111001011100 %
1"
#3300000
0"
#3310000
b11111111 !
b11111111 &
b100000001010000 %
1"
#3320000
0"
#3330000
b11111110 !
b11111110 &
b100001001000100 %
1"
#3340000
0"
#3350000
b100010000111000 %
1"
#3360000
0"
#3370000
b11111101 !
b11111101 &
b100011000101100 %
1"
#3380000
0"
#3390000
b11111100 !
b11111100 &
b100100000100000 %
1"
#3400000
0"
#3410000
b11111011 !
b11111011 &
b100101000010100 %
1"
#3420000
0"
#3430000
b11111001 !
b11111001 &
b100110000001000 %
1"
#3440000
0"
#3450000
b11111000 !
b11111000 &
b100110111111100 %
1"
#3460000
0"
#3470000
b11110110 !
b11110110 &
b100111111110000 %
1"
#3480000
0"
#3490000
b11110100 !
b11110100 &
b101000111100100 %
1"
#3500000
0"
#3510000
b11110001 !
b11110001 &
b101001111011000 %
1"
#3520000
0"
#3530000
b11101110 !
b11101110 &
b101010111001100 %
1"
#3540000
0"
#3550000
b11101011 !
b11101011 &
b101011111000000 %
1"
#3560000
0"
#3570000
b11100111 !
b11100111 &
b101100110110100 %
1"
#3580000
0"
#3590000
b11100100 !
b11100100 &
b101101110101000 %
1"
#3600000
0"
#3610000
b11100000 !
b11100000 &
b101110110011100 %
1"
#3620000
0"
#3630000
b11011011 !
b11011011 &
b101111110010000 %
1"
#3640000
0"
#3650000
b11010111 !
b11010111 &
b110000110000100 %
1"
#3660000
0"
#3670000
b11010010 !
b11010010 &
b110001101111000 %
1"
#3680000
0"
#3690000
b11001101 !
b11001101 &
b110010101101100 %
1"
#3700000
0"
#3710000
b11001000 !
b11001000 &
b110011101100000 %
1"
#3720000
0"
#3730000
b11000011 !
b11000011 &
b110100101010100 %
1"
#3740000
0"
#3750000
b10111110 !
b10111110 &
b110101101001000 %
1"
#3760000
0"
#3770000
b10111000 !
b10111000 &
b110110100111100 %
1"
#3780000
0"
#3790000
b10110011 !
b10110011 &
b110111100110000 %
1"
#3800000
0"
#3810000
b10101101 !
b10101101 &
b111000100100100 %
1"
#3820000
0"
#3830000
b10100111 !
b10100111 &
b111001100011000 %
1"
#3840000
0"
#3850000
b10100001 !
b10100001 &
b111010100001100 %
1"
#3860000
0"
#3870000
b10011011 !
b10011011 &
b111011100000000 %
1"
#3880000
0"
#3890000
b10011000 !
b10011000 &
b111100011110100 %
1"
#3900000
0"
#3910000
b10010010 !
b10010010 &
b111101011101000 %
1"
#3920000
0"
#3930000
b10001011 !
b10001011 &
b111110011011100 %
1"
#3940000
0"
#3950000
b10000101 !
b10000101 &
b111111011010000 %
1"
#3960000
0"
#3970000
b1111111 !
b1111111 &
b1000000011000100 %
1"
#3980000
0"
#3990000
b1111001 !
b1111001 &
b1000001010111000 %
1"
#4000000
0"
#4010000
b1110011 !
b1110011 &
b1000010010101100 %
1"
#4020000
0"
#4030000
b1101100 !
b1101100 &
b1000011010100000 %
1"
#4040000
0"
#4050000
b1100110 !
b1100110 &
b1000100010010100 %
1"
#4060000
0"
#4070000
b1100000 !
b1100000 &
b1000101010001000 %
1"
#4080000
0"
#4090000
b1011010 !
b1011010 &
b1000110001111100 %
1"
#4100000
0"
#4110000
b1010100 !
b1010100 &
b1000111001110000 %
1"
#4120000
0"
#4130000
b1001110 !
b1001110 &
b1001000001100100 %
1"
#4140000
0"
#4150000
b1001000 !
b1001000 &
b1001001001011000 %
1"
#4160000
0"
#4170000
b1000011 !
b1000011 &
b1001010001001100 %
1"
#4180000
0"
#4190000
b111101 !
b111101 &
b1001011001000000 %
1"
#4200000
0"
#4210000
b111000 !
b111000 &
b1001100000110100 %
1"
#4220000
0"
#4230000
b110011 !
b110011 &
b1001101000101000 %
1"
#4240000
0"
#4250000
b101110 !
b101110 &
b1001110000011100 %
1"
#4260000
0"
#4270000
b101001 !
b101001 &
b1001111000010000 %
1"
#4280000
0"
#4290000
b100101 !
b100101 &
b1010000000000100 %
1"
#4300000
0"
#4310000
b100011 !
b100011 &
b1010000111111000 %
1"
#4320000
0"
#4330000
b11110 !
b11110 &
b1010001111101100 %
1"
#4340000
0"
#4350000
b11010 !
b11010 &
b1010010111100000 %
1"
#4360000
0"
#4370000
b10111 !
b10111 &
b1010011111010100 %
1"
#4380000
0"
#4390000
b10011 !
b10011 &
b1010100111001000 %
1"
#4400000
0"
#4410000
b10000 !
b10000 &
b1010101110111100 %
1"
#4420000
0"
#4430000
b1101 !
b1101 &
b1010110110110000 %
1"
#4440000
0"
#4450000
b1010 !
b1010 &
b1010111110100100 %
1"
#4460000
0"
#4470000
b1000 !
b1000 &
b1011000110011000 %
1"
#4480000
0"
#4490000
b110 !
b110 &
b1011001110001100 %
1"
#4500000
0"
#4510000
b100 !
b100 &
b1011010110000000 %
1"
#4520000
0"
#4530000
b11 !
b11 &
b1011011101110100 %
1"
#4540000
0"
#4550000
b1 !
b1 &
b1011100101101000 %
1"
#4560000
0"
#4570000
b0 !
b0 &
b1011101101011100 %
1"
#4580000
0"
#4590000
b1011110101010000 %
1"
#4600000
0"
#4610000
b1011111101000100 %
1"
#4620000
0"
#4630000
b1100000100111000 %
1"
#4640000
0"
#4650000
b1100001100101100 %
1"
#4660000
0"
#4670000
b1100010100100000 %
1"
#4680000
0"
#4690000
b1 !
b1 &
b1100011100010100 %
1"
#4700000
0"
#4710000
b11 !
b11 &
b1100100100001000 %
1"
#4720000
0"
#4730000
b1100101011111100 %
1"
#4740000
0"
#4750000
b101 !
b101 &
b1100110011110000 %
1"
#4760000
0"
#4770000
b111 !
b111 &
b1100111011100100 %
1"
#4780000
0"
#4790000
b1001 !
b1001 &
b1101000011011000 %
1"
#4800000
0"
#4810000
b1100 !
b1100 &
b1101001011001100 %
1"
#4820000
0"
#4830000
b1111 !
b1111 &
b1101010011000000 %
1"
#4840000
0"
#4850000
b10010 !
b10010 &
b1101011010110100 %
1"
#4860000
0"
#4870000
b10101 !
b10101 &
b1101100010101000 %
1"
#4880000
0"
#4890000
b11001 !
b11001 &
b1101101010011100 %
1"
#4900000
0"
#4910000
b11100 !
b11100 &
b1101110010010000 %
1"
#4920000
0"
#4930000
b100001 !
b100001 &
b1101111010000100 %
1"
#4940000
0"
#4950000
b100101 !
b100101 &
b1110000001111000 %
1"
#4960000
0"
#4970000
b101001 !
b101001 &
b1110001001101100 %
1"
#4980000
0"
#4990000
b101110 !
b101110 &
b1110010001100000 %
1"
#5000000
0"
#5010000
b110011 !
b110011 &
b1110011001010100 %
1"
#5020000
0"
#5030000
b111000 !
b111000 &
b1110100001001000 %
1"
#5040000
0"
#5050000
b111101 !
b111101 &
b1110101000111100 %
1"
#5060000
0"
#5070000
b1000011 !
b1000011 &
b1110110000110000 %
1"
#5080000
0"
#5090000
b1001000 !
b1001000 &
b1110111000100100 %
1"
#5100000
0"
#5110000
b1001110 !
b1001110 &
b1111000000011000 %
1"
#5120000
0"
#5130000
b1010100 !
b1010100 &
b1111001000001100 %
1"
#5140000
0"
#5150000
b1011010 !
b1011010 &
b1111010000000000 %
1"
#5160000
0"
#5170000
b1011101 !
b1011101 &
b1111010111110100 %
1"
#5180000
0"
#5190000
b1100011 !
b1100011 &
b1111011111101000 %
1"
#5200000
0"
#5210000
b1101001 !
b1101001 &
b1111100111011100 %
1"
#5220000
0"
#5230000
b1101111 !
b1101111 &
b1111101111010000 %
1"
#5240000
0"
#5250000
b1110110 !
b1110110 &
b1111110111000100 %
1"
#5260000
0"
#5270000
b1111100 !
b1111100 &
b1111111110111000 %
1"
#5280000
0"
#5290000
b10000010 !
b10000010 &
b110101100 %
1"
#5300000
0"
#5310000
b10001000 !
b10001000 &
b1110100000 %
1"
#5320000
0"
#5330000
b10001111 !
b10001111 &
b10110010100 %
1"
#5340000
0"
#5350000
b10010101 !
b10010101 &
b11110001000 %
1"
#5360000
0"
#5370000
b10011011 !
b10011011 &
b100101111100 %
1"
#5380000
0"
#5390000
b10100001 !
b10100001 &
b101101110000 %
1"
#5400000
0"
#5410000
b10100111 !
b10100111 &
b110101100100 %
1"
#5420000
0"
#5430000
b10101101 !
b10101101 &
b111101011000 %
1"
#5440000
0"
#5450000
b10110011 !
b10110011 &
b1000101001100 %
1"
#5460000
0"
#5470000
b10111000 !
b10111000 &
b1001101000000 %
1"
#5480000
0"
#5490000
b10111110 !
b10111110 &
b1010100110100 %
1"
#5500000
0"
#5510000
b11000011 !
b11000011 &
b1011100101000 %
1"
#5520000
0"
#5530000
b11001000 !
b11001000 &
b1100100011100 %
1"
#5540000
0"
#5550000
b11001101 !
b11001101 &
b1101100010000 %
1"
#5560000
0"
#5570000
b11010010 !
b11010010 &
b1110100000100 %
1"
#5580000
0"
#5590000
b11010101 !
b11010101 &
b1111011111000 %
1"
#5600000
0"
#5610000
b11011001 !
b11011001 &
b10000011101100 %
1"
#5620000
0"
#5630000
b11011101 !
b11011101 &
b10001011100000 %
1"
#5640000
0"
#5650000
b11100010 !
b11100010 &
b10010011010100 %
1"
#5660000
0"
#5670000
b11100101 !
b11100101 &
b10011011001000 %
1"
#5680000
0"
#5690000
b11101001 !
b11101001 &
b10100010111100 %
1"
#5700000
0"
#5710000
b11101100 !
b11101100 &
b10101010110000 %
1"
#5720000
0"
#5730000
b11101111 !
b11101111 &
b10110010100100 %
1"
#5740000
0"
#5750000
b11110010 !
b11110010 &
b10111010011000 %
1"
#5760000
0"
#5770000
b11110101 !
b11110101 &
b11000010001100 %
1"
#5780000
0"
#5790000
b11110111 !
b11110111 &
b11001010000000 %
1"
#5800000
0"
#5810000
b11111001 !
b11111001 &
b11010001110100 %
1"
#5820000
0"
#5830000
b11111011 !
b11111011 &
b11011001101000 %
1"
#5840000
0"
#5850000
b11111100 !
b11111100 &
b11100001011100 %
1"
#5860000
0"
#5870000
b11111101 !
b11111101 &
b11101001010000 %
1"
#5880000
0"
#5890000
b11111110 !
b11111110 &
b11110001000100 %
1"
#5900000
0"
#5910000
b11111000111000 %
1"
#5920000
0"
#5930000
b11111111 !
b11111111 &
b100000000101100 %
1"
#5940000
0"
#5950000
b11111110 !
b11111110 &
b100001000100000 %
1"
#5960000
0"
#5970000
b100010000010100 %
1"
#5980000
0"
#5990000
b11111101 !
b11111101 &
b100011000001000 %
1"
#6000000
0"
#6010000
b100011111111100 %
1"
#6020000
0"
#6030000
b11111011 !
b11111011 &
b100100111110000 %
1"
#6040000
0"
#6050000
b11111010 !
b11111010 &
b100101111100100 %
1"
#6060000
0"
#6070000
b11111000 !
b11111000 &
b100110111011000 %
1"
#6080000
0"
#6090000
b11110110 !
b11110110 &
b100111111001100 %
1"
#6100000
0"
#6110000
b11110100 !
b11110100 &
b101000111000000 %
1"
#6120000
0"
#6130000
b11110001 !
b11110001 &
b101001110110100 %
1"
#6140000
0"
#6150000
b11101110 !
b11101110 &
b101010110101000 %
1"
#6160000
0"
#6170000
b11101011 !
b11101011 &
b101011110011100 %
1"
#6180000
0"
#6190000
b11100111 !
b11100111 &
b101100110010000 %
1"
#6200000
0"
#6210000
b11100100 !
b11100100 &
b101101110000100 %
1"
#6220000
0"
#6230000
b11100000 !
b11100000 &
b101110101111000 %
1"
#6240000
0"
#6250000
b11011011 !
b11011011 &
b101111101101100 %
1"
#6260000
0"
#6270000
b11010111 !
b11010111 &
b110000101100000 %
1"
#6280000
0"
#6290000
b11010010 !
b11010010 &
b110001101010100 %
1"
#6300000
0"
#6310000
b11001101 !
b11001101 &
b110010101001000 %
1"
#6320000
0"
#6330000
b11001000 !
b11001000 &
b110011100111100 %
1"
#6340000
0"
#6350000
b11000011 !
b11000011 &
b110100100110000 %
1"
#6360000
0"
#6370000
b10111110 !
b10111110 &
b110101100100100 %
1"
#6380000
0"
#6390000
b10111000 !
b10111000 &
b110110100011000 %
1"
#6400000
0"
#6410000
b10110011 !
b10110011 &
b110111100001100 %
1"
#6420000
0"
#6430000
b10101101 !
b10101101 &
b111000100000000 %
1"
#6440000
0"
#6450000
b10101010 !
b10101010 &
b111001011110100 %
1"
#6460000
0"
#6470000
b10100100 !
b10100100 &
b111010011101000 %
1"
#6480000
0"
#6490000
b10011110 !
b10011110 &
b111011011011100 %
1"
#6500000
0"
#6510000
b10011000 !
b10011000 &
b111100011010000 %
1"
#6520000
0"
#6530000
b10010010 !
b10010010 &
b111101011000100 %
1"
#6540000
0"
#6550000
b10001011 !
b10001011 &
b111110010111000 %
1"
#6560000
0"
#6570000
b10000101 !
b10000101 &
b111111010101100 %
1"
#6580000
0"
#6590000
b1111111 !
b1111111 &
b1000000010100000 %
1"
#6600000
0"
#6610000
b1111001 !
b1111001 &
b1000001010010100 %
1"
#6620000
0"
#6630000
b1110011 !
b1110011 &
b1000010010001000 %
1"
#6640000
0"
#6650000
b1101100 !
b1101100 &
b1000011001111100 %
1"
#6660000
0"
#6670000
b1100110 !
b1100110 &
b1000100001110000 %
1"
#6680000
0"
#6690000
b1100000 !
b1100000 &
b1000101001100100 %
1"
#6700000
0"
#6710000
b1011010 !
b1011010 &
b1000110001011000 %
1"
#6720000
0"
#6730000
b1010100 !
b1010100 &
b1000111001001100 %
1"
#6740000
0"
#6750000
b1001110 !
b1001110 &
b1001000001000000 %
1"
#6760000
0"
#6770000
b1001000 !
b1001000 &
b1001001000110100 %
1"
#6780000
0"
#6790000
b1000011 !
b1000011 &
b1001010000101000 %
1"
#6800000
0"
#6810000
b111101 !
b111101 &
b1001011000011100 %
1"
#6820000
0"
#6830000
b111000 !
b111000 &
b1001100000010000 %
1"
#6840000
0"
#6850000
b110011 !
b110011 &
b1001101000000100 %
1"
#6860000
0"
#6870000
b110001 !
b110001 &
b1001101111111000 %
1"
#6880000
0"
#6890000
b101100 !
b101100 &
b1001110111101100 %
1"
#6900000
0"
#6910000
b100111 !
b100111 &
b1001111111100000 %
1"
#6920000
0"
#6930000
b100011 !
b100011 &
b1010000111010100 %
1"
#6940000
0"
#6950000
b11110 !
b11110 &
b1010001111001000 %
1"
#6960000
0"
#6970000
b11010 !
b11010 &
b1010010110111100 %
1"
#6980000
0"
#6990000
b10111 !
b10111 &
b1010011110110000 %
1"
#7000000
0"
#7010000
b10011 !
b10011 &
b1010100110100100 %
1"
#7020000
0"
#7030000
b10000 !
b10000 &
b1010101110011000 %
1"
#7040000
0"
#7050000
b1101 !
b1101 &
b1010110110001100 %
1"
#7060000
0"
#7070000
b1010 !
b1010 &
b1010111110000000 %
1"
#7080000
0"
#7090000
b1000 !
b1000 &
b1011000101110100 %
1"
#7100000
0"
#7110000
b110 !
b110 &
b1011001101101000 %
1"
#7120000
0"
#7130000
b100 !
b100 &
b1011010101011100 %
1"
#7140000
0"
#7150000
b11 !
b11 &
b1011011101010000 %
1"
#7160000
0"
#7170000
b1 !
b1 &
b1011100101000100 %
1"
#7180000
0"
#7190000
b0 !
b0 &
b1011101100111000 %
1"
#7200000
0"
#7210000
b1011110100101100 %
1"
#7220000
0"
#7230000
b1011111100100000 %
1"
#7240000
0"
#7250000
b1100000100010100 %
1"
#7260000
0"
#7270000
b1100001100001000 %
1"
#7280000
0"
#7290000
b1100010011111100 %
1"
#7300000
0"
#7310000
b1 !
b1 &
b1100011011110000 %
1"
#7320000
0"
#7330000
b10 !
b10 &
b1100100011100100 %
1"
#7340000
0"
#7350000
b11 !
b11 &
b1100101011011000 %
1"
#7360000
0"
#7370000
b101 !
b101 &
b1100110011001100 %
1"
#7380000
0"
#7390000
b111 !
b111 &
b1100111011000000 %
1"
#7400000
0"
#7410000
b1001 !
b1001 &
b1101000010110100 %
1"
#7420000
0"
#7430000
b1100 !
b1100 &
b1101001010101000 %
1"
#7440000
0"
#7450000
b1111 !
b1111 &
b1101010010011100 %
1"
#7460000
0"
#7470000
b10010 !
b10010 &
b1101011010010000 %
1"
#7480000
0"
#7490000
b10101 !
b10101 &
b1101100010000100 %
1"
